puree-1.0.2.data/data/man/man1/puree.1
puree-1.0.2.data/scripts/puree
pureelib/__init__.py
pureelib/plumbing/__init__.py
pureelib/plumbing/common.py
pureelib/plumbing/destroy.py
pureelib/plumbing/format.py
pureelib/plumbing/show.py
pureelib/plumbing/subspecs.py
pureelib/plumbing/unpack.py
pureelib/porcelain/__init__.py
pureelib/porcelain/__main__.py
pureelib/porcelain/destroy.py
pureelib/porcelain/format.py
pureelib/porcelain/help.py
pureelib/porcelain/info.py
pureelib/porcelain/map.py
pureelib/porcelain/puree_main.py
pureelib/porcelain/unmap.py
puree-1.0.2.dist-info/LICENSE
puree-1.0.2.dist-info/METADATA
puree-1.0.2.dist-info/WHEEL
puree-1.0.2.dist-info/top_level.txt
puree-1.0.2.dist-info/RECORD
