Metadata-Version: 2.1
Name: puree
Version: 1.0.2
Summary: PUREE: Password-based Uniform-Random-Equivalent Encryption
Home-page: https://puree.cc
Author: Jay Sullivan
Author-email: jay@identity.pub
License: UNKNOWN
Platform: UNKNOWN
Classifier: Programming Language :: Python :: 3.6
Classifier: License :: Public Domain
Classifier: Operating System :: POSIX :: Linux
Requires-Python: >=3.6
Requires-Dist: pysodium (>=0.7.5)
Requires-Dist: pysodium (<1.0.0)
Requires-Dist: argon2-cffi (>=20.1.0)
Requires-Dist: argon2-cffi (<21.0.0)
